appsettings/__init__.py
appsettings/settings.py
appsettings/validators.py
django_app_settings-0.6.1.dist-info/AUTHORS.rst
django_app_settings-0.6.1.dist-info/LICENSE
django_app_settings-0.6.1.dist-info/METADATA
django_app_settings-0.6.1.dist-info/WHEEL
django_app_settings-0.6.1.dist-info/top_level.txt
django_app_settings-0.6.1.dist-info/RECORD
