Metadata-Version: 2.1
Name: django-app-settings
Version: 0.6.1
Summary: Application settings helper for Django apps.
Home-page: https://github.com/Genida/django-appsettings
Author: Timothee Mazzucotelli
Author-email: timothee.mazzucotelli@gmail.com
License: ISC
Keywords: django,app,settings
Platform: UNKNOWN
Classifier: Development Status :: 4 - Beta
Classifier: Intended Audience :: Developers
Classifier: License :: OSI Approved :: ISC License (ISCL)
Classifier: Operating System :: Unix
Classifier: Framework :: Django
Classifier: Programming Language :: Python
Classifier: Programming Language :: Python :: 2.7
Classifier: Programming Language :: Python :: 3
Classifier: Programming Language :: Python :: 3.4
Classifier: Programming Language :: Python :: 3.5
Classifier: Programming Language :: Python :: 3.6
Classifier: Programming Language :: Python :: Implementation :: PyPy
Classifier: Topic :: Utilities
Requires-Dist: six
